{"version":1.3,"people":[{"person_id":[-1],"pose_keypoints_2d":[0,0,0,0,0,0,0,0,0,0,0,0,0,0,0,0,0,0,0,0,0,0,0,0,0,0,0,0,0,0,0,0,0,0,0,0,0,0,0,482.717,280.023,0.335312,510.662,727.38,0.584038,0,0,0,0,0,0,0,0,0,0,0,0,688.932,797.313,0.477591,685.474,783.33,0.428599,475.763,765.789,0.544576,0,0,0,0,0,0,0,0,0],"face_keypoints_2d":[],"hand_left_keypoints_2d":[],"hand_right_keypoints_2d":[],"pose_keypoints_3d":[],"face_keypoints_3d":[],"hand_left_keypoints_3d":[],"hand_right_keypoints_3d":[]},{"person_id":[-1],"pose_keypoints_2d":[0,0,0,0,0,0,0,0,0,0,0,0,0,0,0,0,0,0,0,0,0,0,0,0,0,0,0,0,0,0,311.521,283.572,0.334832,273.116,716.924,0.609862,0,0,0,0,0,0,0,0,0,0,0,0,0,0,0,0,0,0,0,0,0,0,0,0,0,0,0,0,0,0,77.369,797.257,0.391701,80.9165,783.31,0.346812,297.591,748.359,0.507434],"face_keypoints_2d":[],"hand_left_keypoints_2d":[],"hand_right_keypoints_2d":[],"pose_keypoints_3d":[],"face_keypoints_3d":[],"hand_left_keypoints_3d":[],"hand_right_keypoints_3d":[]}]}