{"version":1.3,"people":[{"person_id":[-1],"pose_keypoints_2d":[0,0,0,0,0,0,0,0,0,0,0,0,0,0,0,0,0,0,0,0,0,0,0,0,0,0,0,0,0,0,0,0,0,0,0,0,0,0,0,284.38,216.869,0.451295,272.707,493.791,0.399409,0,0,0,0,0,0,0,0,0,0,0,0,379.729,531.062,0.240473,379.754,526.301,0.223629,0,0,0,0,0,0,0,0,0,0,0,0],"face_keypoints_2d":[],"hand_left_keypoints_2d":[],"hand_right_keypoints_2d":[],"pose_keypoints_3d":[],"face_keypoints_3d":[],"hand_left_keypoints_3d":[],"hand_right_keypoints_3d":[]},{"person_id":[-1],"pose_keypoints_2d":[0,0,0,0,0,0,0,0,0,0,0,0,0,0,0,0,0,0,0,0,0,0,0,0,0,0,0,175.08,6.2829,0.0678232,195.98,216.939,0.384766,212.211,484.497,0.292665,0,0,0,0,0,0,0,0,0,0,0,0,0,0,0,0,0,0,0,0,0,0,0,0,0,0,0,0,0,0,116.843,524.006,0.0677461,0,0,0,0,0,0],"face_keypoints_2d":[],"hand_left_keypoints_2d":[],"hand_right_keypoints_2d":[],"pose_keypoints_3d":[],"face_keypoints_3d":[],"hand_left_keypoints_3d":[],"hand_right_keypoints_3d":[]},{"person_id":[-1],"pose_keypoints_2d":[0,0,0,0,0,0,0,0,0,0,0,0,0,0,0,0,0,0,0,0,0,0,0,0,0,0,0,0,0,0,279.764,221.54,0.249209,277.392,493.755,0.278267,0,0,0,0,0,0,0,0,0,0,0,0,0,0,0,0,0,0,0,0,0,0,0,0,0,0,0,0,0,0,386.773,531.013,0.340795,368.126,542.631,0.299831,251.804,521.674,0.272034],"face_keypoints_2d":[],"hand_left_keypoints_2d":[],"hand_right_keypoints_2d":[],"pose_keypoints_3d":[],"face_keypoints_3d":[],"hand_left_keypoints_3d":[],"hand_right_keypoints_3d":[]},{"person_id":[-1],"pose_keypoints_2d":[0,0,0,0,0,0,0,0,0,0,0,0,0,0,0,0,0,0,0,0,0,0,0,0,0,0,0,0,0,0,0,0,0,0,0,0,0,0,0,200.601,226.195,0.328789,205.245,493.757,0.341307,0,0,0,0,0,0,0,0,0,0,0,0,107.548,521.686,0.346128,123.809,528.664,0.307043,230.899,519.39,0.443628,0,0,0,0,0,0,0,0,0],"face_keypoints_2d":[],"hand_left_keypoints_2d":[],"hand_right_keypoints_2d":[],"pose_keypoints_3d":[],"face_keypoints_3d":[],"hand_left_keypoints_3d":[],"hand_right_keypoints_3d":[]}]}