{"version":1.3,"people":[{"person_id":[-1],"pose_keypoints_2d":[0,0,0,0,0,0,0,0,0,0,0,0,0,0,0,0,0,0,0,0,0,0,0,0,0,0,0,0,0,0,0,0,0,0,0,0,314.993,9.22301,0.122499,405.764,342.996,0.623937,465.239,765.846,0.697047,0,0,0,0,0,0,0,0,0,0,0,0,297.571,821.76,0.378058,332.467,839.22,0.372602,496.706,804.307,0.563794,0,0,0,0,0,0,0,0,0],"face_keypoints_2d":[],"hand_left_keypoints_2d":[],"hand_right_keypoints_2d":[],"pose_keypoints_3d":[],"face_keypoints_3d":[],"hand_left_keypoints_3d":[],"hand_right_keypoints_3d":[]},{"person_id":[-1],"pose_keypoints_2d":[0,0,0,0,0,0,0,0,0,0,0,0,0,0,0,0,0,0,0,0,0,0,0,0,0,0,0,0,0,0,381.441,311.513,0.42728,335.951,748.366,0.57388,0,0,0,0,0,0,0,0,0,0,0,0,0,0,0,0,0,0,0,0,0,0,0,0,0,0,0,0,0,0,269.613,842.622,0.260931,0,0,0,367.332,765.766,0.224653],"face_keypoints_2d":[],"hand_left_keypoints_2d":[],"hand_right_keypoints_2d":[],"pose_keypoints_3d":[],"face_keypoints_3d":[],"hand_left_keypoints_3d":[],"hand_right_keypoints_3d":[]}]}